enricher/__init__.py
enricher/enricher.py
enricher-0.1.0.dist-info/METADATA
enricher-0.1.0.dist-info/WHEEL
enricher-0.1.0.dist-info/top_level.txt
enricher-0.1.0.dist-info/RECORD
